PushingBox/__init__.py
PushingBox-0.1.3.dist-info/DESCRIPTION.rst
PushingBox-0.1.3.dist-info/METADATA
PushingBox-0.1.3.dist-info/RECORD
PushingBox-0.1.3.dist-info/WHEEL
PushingBox-0.1.3.dist-info/metadata.json
PushingBox-0.1.3.dist-info/top_level.txt
